pay_client/__init__.py
pay_client/clients/__init__.py
pay_client/clients/abstract.py
pay_client/clients/alipay.py
pay_client/clients/mock.py
pay_client/configs/__init__.py
pay_client/configs/abstract.py
pay_client/configs/alipay.py
pay_client/configs/mock.py
pay_client/enums/__init__.py
pay_client/enums/order.py
pay_client/models/__init__.py
pay_client/models/order.py
pay_client/models/refund.py
pay_client-0.1.1.dist-info/METADATA
pay_client-0.1.1.dist-info/WHEEL
pay_client-0.1.1.dist-info/RECORD
