Metadata-Version: 2.1
Name: pay-client
Version: 0.1.1
Summary: 
Author: NGYF
Author-email: 1605146531@qq.com
Requires-Python: >=3.12,<4.0
Classifier: Programming Language :: Python :: 3
Classifier: Programming Language :: Python :: 3.12
Classifier: Programming Language :: Python :: 3.13
Requires-Dist: alipay-sdk-python (>=3.7.345,<4.0.0)
Requires-Dist: pydantic (>=2.0,<3.0.0)
